graphlog/__init__.py
graphlog/dataset.py
graphlog/graphlog.py
graphlog/types.py
graphlog/utils.py
graphlog-1.0.0.dist-info/LICENSE
graphlog-1.0.0.dist-info/METADATA
graphlog-1.0.0.dist-info/WHEEL
graphlog-1.0.0.dist-info/top_level.txt
graphlog-1.0.0.dist-info/RECORD
