Metadata-Version: 2.1
Name: graphlog
Version: 1.0.0
Summary: API to interface with the GraphLog Dataset
Home-page: UNKNOWN
Author: Koustuv Sinha and Shagun Sodhani
Author-email: sshagunsodhani@gmail.com
License: UNKNOWN
Platform: UNKNOWN
Classifier: Programming Language :: Python :: 3.6
Classifier: Programming Language :: Python :: 3.7
Classifier: Programming Language :: Python :: 3.8
Classifier: License :: OSI Approved :: MIT License
Classifier: Operating System :: OS Independent
Requires-Python: >=3.6
Requires-Dist: tqdm (==4.43.0)
Requires-Dist: numpy (==1.18.1)
Requires-Dist: networkx (==2.4)
Requires-Dist: addict (==2.2.1)
Provides-Extra: dev
Requires-Dist: black (==19.10b) ; extra == 'dev'
Requires-Dist: flake8 (==3.7.9) ; extra == 'dev'
Requires-Dist: flake8-bugbear (==20.1.4) ; extra == 'dev'
Requires-Dist: flake8-comprehensions (==3.2.2) ; extra == 'dev'
Requires-Dist: mypy (==0.740) ; extra == 'dev'
Requires-Dist: nox (==2019.11.9) ; extra == 'dev'
Requires-Dist: pre-commit (==2.0.1) ; extra == 'dev'
Requires-Dist: typing-extensions (==3.7.4.1) ; extra == 'dev'
Requires-Dist: pytest (==5.3.5) ; extra == 'dev'
Requires-Dist: tqdm (==4.43.0) ; extra == 'dev'
Requires-Dist: numpy (==1.18.1) ; extra == 'dev'
Requires-Dist: networkx (==2.4) ; extra == 'dev'
Requires-Dist: addict (==2.2.1) ; extra == 'dev'
